{
  "log": "logs/live/gsusb_20260508_204254.txt",
  "start_size": 58091831,
  "end_size": 59537862,
  "frames": 25792,
  "rows": [
    {
      "ch": 1,
      "id_hex": "0x164",
      "dlc": 4,
      "count": 1003,
      "unique": 16,
      "changing_bytes": [
        2,
        3
      ],
      "first": "00 08 02 0A",
      "last": "00 08 16 1E",
      "top": [
        {
          "data": "00 08 02 0A",
          "count": 63
        },
        {
          "data": "00 08 04 0C",
          "count": 63
        },
        {
          "data": "00 08 06 0E",
          "count": 63
        },
        {
          "data": "00 08 08 00",
          "count": 63
        },
        {
          "data": "00 08 0A 02",
          "count": 63
        },
        {
          "data": "00 08 0C 04",
          "count": 63
        },
        {
          "data": "00 08 0E 06",
          "count": 63
        },
        {
          "data": "00 08 10 18",
          "count": 63
        },
        {
          "data": "00 08 12 1A",
          "count": 63
        },
        {
          "data": "00 08 14 1C",
          "count": 63
        },
        {
          "data": "00 08 16 1E",
          "count": 63
        },
        {
          "data": "00 08 18 10",
          "count": 62
        }
      ]
    },
    {
      "ch": 1,
      "id_hex": "0x220",
      "dlc": 8,
      "count": 1003,
      "unique": 806,
      "changing_bytes": [
        0,
        1,
        2,
        5,
        7
      ],
      "first": "08 C4 7F 00 00 59 10 1D",
      "last": "0A 84 7F 00 00 53 10 B9",
      "top": [
        {
          "data": "0B E4 7F 00 00 59 10 7E",
          "count": 5
        },
        {
          "data": "09 E4 7F 00 00 5C 10 F1",
          "count": 5
        },
        {
          "data": "09 E4 7F 00 00 60 10 F5",
          "count": 4
        },
        {
          "data": "09 E4 7F 00 00 59 10 4C",
          "count": 4
        },
        {
          "data": "0B C4 7F 00 00 59 10 EE",
          "count": 4
        },
        {
          "data": "09 E4 7F 00 00 59 10 0C",
          "count": 4
        },
        {
          "data": "08 E4 7F 00 00 55 10 69",
          "count": 3
        },
        {
          "data": "0B E4 7F 00 00 57 10 1C",
          "count": 3
        },
        {
          "data": "0B E4 7F 00 00 57 10 EC",
          "count": 3
        },
        {
          "data": "0B E4 7F 00 00 59 10 AE",
          "count": 3
        },
        {
          "data": "08 E4 7F 00 00 55 10 49",
          "count": 3
        },
        {
          "data": "0B E4 7F 00 00 59 10 1E",
          "count": 3
        }
      ]
    },
    {
      "ch": 1,
      "id_hex": "0x251",
      "dlc": 8,
      "count": 1003,
      "unique": 720,
      "changing_bytes": [
        0,
        2,
        3,
        5,
        6
      ],
      "first": "2A 04 88 40 00 22 E8 80",
      "last": "28 04 72 06 00 20 C8 80",
      "top": [
        {
          "data": "28 04 E4 78 00 20 C8 80",
          "count": 4
        },
        {
          "data": "28 04 EB 7F 00 20 C8 80",
          "count": 4
        },
        {
          "data": "28 04 09 9D 00 20 C8 80",
          "count": 4
        },
        {
          "data": "28 04 0B 9F 00 20 C8 80",
          "count": 4
        },
        {
          "data": "28 04 29 BD 00 20 C8 80",
          "count": 4
        },
        {
          "data": "2A 04 96 2E 00 22 C8 80",
          "count": 3
        },
        {
          "data": "28 04 9B 4F 00 20 E8 80",
          "count": 3
        },
        {
          "data": "28 04 AC 40 00 20 C8 80",
          "count": 3
        },
        {
          "data": "28 04 CA 5E 00 20 C8 80",
          "count": 3
        },
        {
          "data": "28 04 D0 64 00 20 C8 80",
          "count": 3
        },
        {
          "data": "28 04 D1 65 00 20 C8 80",
          "count": 3
        },
        {
          "data": "28 04 D7 6B 00 20 C8 80",
          "count": 3
        }
      ]
    },
    {
      "ch": 1,
      "id_hex": "0x386",
      "dlc": 8,
      "count": 502,
      "unique": 16,
      "changing_bytes": [
        1,
        3
      ],
      "first": "00 C0 00 80 00 40 00 80",
      "last": "00 00 00 00 00 40 00 80",
      "top": [
        {
          "data": "00 C0 00 80 00 40 00 80",
          "count": 32
        },
        {
          "data": "00 00 00 C0 00 40 00 80",
          "count": 32
        },
        {
          "data": "00 40 00 C0 00 40 00 80",
          "count": 32
        },
        {
          "data": "00 80 00 C0 00 40 00 80",
          "count": 32
        },
        {
          "data": "00 C0 00 C0 00 40 00 80",
          "count": 32
        },
        {
          "data": "00 00 00 00 00 40 00 80",
          "count": 32
        },
        {
          "data": "00 40 00 00 00 40 00 80",
          "count": 31
        },
        {
          "data": "00 80 00 00 00 40 00 80",
          "count": 31
        },
        {
          "data": "00 C0 00 00 00 40 00 80",
          "count": 31
        },
        {
          "data": "00 00 00 40 00 40 00 80",
          "count": 31
        },
        {
          "data": "00 40 00 40 00 40 00 80",
          "count": 31
        },
        {
          "data": "00 80 00 40 00 40 00 80",
          "count": 31
        }
      ]
    },
    {
      "ch": 1,
      "id_hex": "0x47F",
      "dlc": 6,
      "count": 502,
      "unique": 256,
      "changing_bytes": [
        1
      ],
      "first": "20 78 FF FA 00 00",
      "last": "20 6D FF FA 00 00",
      "top": [
        {
          "data": "20 78 FF FA 00 00",
          "count": 2
        },
        {
          "data": "20 79 FF FA 00 00",
          "count": 2
        },
        {
          "data": "20 7A FF FA 00 00",
          "count": 2
        },
        {
          "data": "20 7B FF FA 00 00",
          "count": 2
        },
        {
          "data": "20 7C FF FA 00 00",
          "count": 2
        },
        {
          "data": "20 7D FF FA 00 00",
          "count": 2
        },
        {
          "data": "20 7E FF FA 00 00",
          "count": 2
        },
        {
          "data": "20 7F FF FA 00 00",
          "count": 2
        },
        {
          "data": "20 80 FF FA 00 00",
          "count": 2
        },
        {
          "data": "20 81 FF FA 00 00",
          "count": 2
        },
        {
          "data": "20 82 FF FA 00 00",
          "count": 2
        },
        {
          "data": "20 83 FF FA 00 00",
          "count": 2
        }
      ]
    },
    {
      "ch": 1,
      "id_hex": "0x5CF",
      "dlc": 8,
      "count": 101,
      "unique": 35,
      "changing_bytes": [
        0,
        1,
        4
      ],
      "first": "3E 23 00 00 12 7F 80 00",
      "last": "3E 22 00 00 00 7F 80 00",
      "top": [
        {
          "data": "3E 23 00 00 10 7F 80 00",
          "count": 13
        },
        {
          "data": "41 21 00 00 11 7F 80 00",
          "count": 10
        },
        {
          "data": "41 21 00 00 0E 7F 80 00",
          "count": 7
        },
        {
          "data": "3E 23 00 00 12 7F 80 00",
          "count": 6
        },
        {
          "data": "3F 23 00 00 0F 7F 80 00",
          "count": 5
        },
        {
          "data": "41 22 00 00 0F 7F 80 00",
          "count": 5
        },
        {
          "data": "41 22 00 00 11 7F 80 00",
          "count": 4
        },
        {
          "data": "3E 22 00 00 10 7F 80 00",
          "count": 4
        },
        {
          "data": "40 22 00 00 0F 7F 80 00",
          "count": 4
        },
        {
          "data": "40 21 00 00 0E 7F 80 00",
          "count": 4
        },
        {
          "data": "40 22 00 00 12 7F 80 00",
          "count": 3
        },
        {
          "data": "41 20 00 00 11 7F 80 00",
          "count": 3
        }
      ]
    },
    {
      "ch": 1,
      "id_hex": "0x38D",
      "dlc": 8,
      "count": 502,
      "unique": 15,
      "changing_bytes": [
        7
      ],
      "first": "00 00 88 00 00 00 00 C4",
      "last": "00 00 88 00 00 00 00 6A",
      "top": [
        {
          "data": "00 00 88 00 00 00 00 C4",
          "count": 34
        },
        {
          "data": "00 00 88 00 00 00 00 B5",
          "count": 34
        },
        {
          "data": "00 00 88 00 00 00 00 A6",
          "count": 34
        },
        {
          "data": "00 00 88 00 00 00 00 97",
          "count": 34
        },
        {
          "data": "00 00 88 00 00 00 00 88",
          "count": 34
        },
        {
          "data": "00 00 88 00 00 00 00 79",
          "count": 34
        },
        {
          "data": "00 00 88 00 00 00 00 6A",
          "count": 34
        },
        {
          "data": "00 00 88 00 00 00 00 5B",
          "count": 33
        },
        {
          "data": "00 00 88 00 00 00 00 4C",
          "count": 33
        },
        {
          "data": "00 00 88 00 00 00 00 3D",
          "count": 33
        },
        {
          "data": "00 00 88 00 00 00 00 2E",
          "count": 33
        },
        {
          "data": "00 00 88 00 00 00 00 00",
          "count": 33
        }
      ]
    },
    {
      "ch": 1,
      "id_hex": "0x420",
      "dlc": 8,
      "count": 502,
      "unique": 16,
      "changing_bytes": [
        0
      ],
      "first": "20 1E 20 C8 B8 4B 6A 00",
      "last": "70 1E 20 C8 B8 4B 6A 00",
      "top": [
        {
          "data": "20 1E 20 C8 B8 4B 6A 00",
          "count": 32
        },
        {
          "data": "30 1E 20 C8 B8 4B 6A 00",
          "count": 32
        },
        {
          "data": "40 1E 20 C8 B8 4B 6A 00",
          "count": 32
        },
        {
          "data": "50 1E 20 C8 B8 4B 6A 00",
          "count": 32
        },
        {
          "data": "60 1E 20 C8 B8 4B 6A 00",
          "count": 32
        },
        {
          "data": "70 1E 20 C8 B8 4B 6A 00",
          "count": 32
        },
        {
          "data": "80 1E 20 C8 B8 4B 6A 00",
          "count": 31
        },
        {
          "data": "90 1E 20 C8 B8 4B 6A 00",
          "count": 31
        },
        {
          "data": "A0 1E 20 C8 B8 4B 6A 00",
          "count": 31
        },
        {
          "data": "B0 1E 20 C8 B8 4B 6A 00",
          "count": 31
        },
        {
          "data": "C0 1E 20 C8 B8 4B 6A 00",
          "count": 31
        },
        {
          "data": "D0 1E 20 C8 B8 4B 6A 00",
          "count": 31
        }
      ]
    },
    {
      "ch": 1,
      "id_hex": "0x421",
      "dlc": 8,
      "count": 502,
      "unique": 15,
      "changing_bytes": [
        7
      ],
      "first": "00 00 00 FF E3 7F 00 74",
      "last": "00 00 00 FF E3 7F 00 1A",
      "top": [
        {
          "data": "00 00 00 FF E3 7F 00 74",
          "count": 34
        },
        {
          "data": "00 00 00 FF E3 7F 00 65",
          "count": 34
        },
        {
          "data": "00 00 00 FF E3 7F 00 56",
          "count": 34
        },
        {
          "data": "00 00 00 FF E3 7F 00 47",
          "count": 34
        },
        {
          "data": "00 00 00 FF E3 7F 00 38",
          "count": 34
        },
        {
          "data": "00 00 00 FF E3 7F 00 29",
          "count": 34
        },
        {
          "data": "00 00 00 FF E3 7F 00 1A",
          "count": 34
        },
        {
          "data": "00 00 00 FF E3 7F 00 0B",
          "count": 33
        },
        {
          "data": "00 00 00 FF E3 7F 00 FC",
          "count": 33
        },
        {
          "data": "00 00 00 FF E3 7F 00 ED",
          "count": 33
        },
        {
          "data": "00 00 00 FF E3 7F 00 DE",
          "count": 33
        },
        {
          "data": "00 00 00 FF E3 7F 00 B0",
          "count": 33
        }
      ]
    },
    {
      "ch": 1,
      "id_hex": "0x4A2",
      "dlc": 2,
      "count": 21,
      "unique": 1,
      "changing_bytes": [],
      "first": "01 00",
      "last": "01 00",
      "top": [
        {
          "data": "01 00",
          "count": 21
        }
      ]
    },
    {
      "ch": 1,
      "id_hex": "0x428",
      "dlc": 8,
      "count": 502,
      "unique": 1,
      "changing_bytes": [],
      "first": "05 00 00 80 60 08 02 00",
      "last": "05 00 00 80 60 08 02 00",
      "top": [
        {
          "data": "05 00 00 80 60 08 02 00",
          "count": 502
        }
      ]
    },
    {
      "ch": 1,
      "id_hex": "0x111",
      "dlc": 8,
      "count": 1003,
      "unique": 370,
      "changing_bytes": [
        5,
        6,
        7
      ],
      "first": "00 40 61 FF 63 11 0A 6C",
      "last": "00 40 61 FF 63 F8 09 A4",
      "top": [
        {
          "data": "00 40 61 FF 63 0C 0A 80",
          "count": 13
        },
        {
          "data": "00 40 61 FF 63 0C 0A 08",
          "count": 9
        },
        {
          "data": "00 40 61 FF 63 12 0A 98",
          "count": 8
        },
        {
          "data": "00 40 61 FF 63 0E 0A AC",
          "count": 8
        },
        {
          "data": "00 40 61 FF 63 06 0A 68",
          "count": 8
        },
        {
          "data": "00 40 61 FF 63 10 0A F4",
          "count": 8
        },
        {
          "data": "00 40 61 FF 63 10 0A 30",
          "count": 7
        },
        {
          "data": "00 40 61 FF 63 10 0A 7C",
          "count": 7
        },
        {
          "data": "00 40 61 FF 63 0F 0A 9C",
          "count": 7
        },
        {
          "data": "00 40 61 FF 63 00 0A 8C",
          "count": 7
        },
        {
          "data": "00 40 61 FF 63 13 0A C4",
          "count": 7
        },
        {
          "data": "00 40 61 FF 63 1D 0A E8",
          "count": 7
        }
      ]
    },
    {
      "ch": 1,
      "id_hex": "0x112",
      "dlc": 8,
      "count": 1003,
      "unique": 370,
      "changing_bytes": [
        1,
        5,
        6
      ],
      "first": "FF F0 00 00 FF 11 0A 00",
      "last": "FF 50 00 00 FF F8 09 00",
      "top": [
        {
          "data": "FF 00 00 00 FF 0C 0A 00",
          "count": 13
        },
        {
          "data": "FF A0 00 00 FF 0C 0A 00",
          "count": 9
        },
        {
          "data": "FF A0 00 00 FF 12 0A 00",
          "count": 8
        },
        {
          "data": "FF F0 00 00 FF 0E 0A 00",
          "count": 8
        },
        {
          "data": "FF A0 00 00 FF 06 0A 00",
          "count": 8
        },
        {
          "data": "FF 50 00 00 FF 10 0A 00",
          "count": 8
        },
        {
          "data": "FF 00 00 00 FF 10 0A 00",
          "count": 7
        },
        {
          "data": "FF F0 00 00 FF 10 0A 00",
          "count": 7
        },
        {
          "data": "FF F0 00 00 FF 0F 0A 00",
          "count": 7
        },
        {
          "data": "FF F0 00 00 FF 00 0A 00",
          "count": 7
        },
        {
          "data": "FF 50 00 00 FF 13 0A 00",
          "count": 7
        },
        {
          "data": "FF A0 00 00 FF 1D 0A 00",
          "count": 7
        }
      ]
    },
    {
      "ch": 1,
      "id_hex": "0x113",
      "dlc": 8,
      "count": 1003,
      "unique": 4,
      "changing_bytes": [
        7
      ],
      "first": "00 20 00 80 00 00 00 AC",
      "last": "00 20 00 80 00 00 00 24",
      "top": [
        {
          "data": "00 20 00 80 00 00 00 AC",
          "count": 251
        },
        {
          "data": "00 20 00 80 00 00 00 60",
          "count": 251
        },
        {
          "data": "00 20 00 80 00 00 00 24",
          "count": 251
        },
        {
          "data": "00 20 00 80 00 00 00 E8",
          "count": 250
        }
      ]
    },
    {
      "ch": 1,
      "id_hex": "0x340",
      "dlc": 8,
      "count": 994,
      "unique": 16,
      "changing_bytes": [
        4,
        6
      ],
      "first": "04 00 00 24 04 00 3D 11",
      "last": "04 00 00 24 14 00 4D 11",
      "top": [
        {
          "data": "04 00 00 24 04 00 3D 11",
          "count": 63
        },
        {
          "data": "04 00 00 24 14 00 4D 11",
          "count": 63
        },
        {
          "data": "04 00 00 24 24 00 5D 11",
          "count": 62
        },
        {
          "data": "04 00 00 24 34 00 6D 11",
          "count": 62
        },
        {
          "data": "04 00 00 24 44 00 7D 11",
          "count": 62
        },
        {
          "data": "04 00 00 24 54 00 8D 11",
          "count": 62
        },
        {
          "data": "04 00 00 24 64 00 9D 11",
          "count": 62
        },
        {
          "data": "04 00 00 24 74 00 AD 11",
          "count": 62
        },
        {
          "data": "04 00 00 24 84 00 BD 11",
          "count": 62
        },
        {
          "data": "04 00 00 24 94 00 CD 11",
          "count": 62
        },
        {
          "data": "04 00 00 24 A4 00 DD 11",
          "count": 62
        },
        {
          "data": "04 00 00 24 B4 00 ED 11",
          "count": 62
        }
      ]
    },
    {
      "ch": 1,
      "id_hex": "0x429",
      "dlc": 8,
      "count": 502,
      "unique": 1,
      "changing_bytes": [],
      "first": "60 02 00 00 00 00 2F 03",
      "last": "60 02 00 00 00 00 2F 03",
      "top": [
        {
          "data": "60 02 00 00 00 00 2F 03",
          "count": 502
        }
      ]
    },
    {
      "ch": 1,
      "id_hex": "0x4F1",
      "dlc": 4,
      "count": 502,
      "unique": 16,
      "changing_bytes": [
        0,
        3
      ],
      "first": "20 00 88 B1",
      "last": "00 00 88 01",
      "top": [
        {
          "data": "20 00 88 B1",
          "count": 32
        },
        {
          "data": "00 00 88 C1",
          "count": 32
        },
        {
          "data": "20 00 88 D1",
          "count": 32
        },
        {
          "data": "20 00 88 E1",
          "count": 32
        },
        {
          "data": "00 00 88 F1",
          "count": 32
        },
        {
          "data": "00 00 88 01",
          "count": 32
        },
        {
          "data": "20 00 88 11",
          "count": 31
        },
        {
          "data": "20 00 88 21",
          "count": 31
        },
        {
          "data": "00 00 88 31",
          "count": 31
        },
        {
          "data": "20 00 88 41",
          "count": 31
        },
        {
          "data": "00 00 88 51",
          "count": 31
        },
        {
          "data": "00 00 88 61",
          "count": 31
        }
      ]
    },
    {
      "ch": 1,
      "id_hex": "0x555",
      "dlc": 8,
      "count": 101,
      "unique": 17,
      "changing_bytes": [
        0,
        2
      ],
      "first": "70 00 6A 00 00 00 00 00",
      "last": "6E 00 70 00 00 00 00 00",
      "top": [
        {
          "data": "6F 00 6C 00 00 00 00 00",
          "count": 16
        },
        {
          "data": "6F 00 6B 00 00 00 00 00",
          "count": 13
        },
        {
          "data": "6E 00 70 00 00 00 00 00",
          "count": 12
        },
        {
          "data": "6E 00 71 00 00 00 00 00",
          "count": 12
        },
        {
          "data": "70 00 69 00 00 00 00 00",
          "count": 11
        },
        {
          "data": "70 00 68 00 00 00 00 00",
          "count": 9
        },
        {
          "data": "70 00 6A 00 00 00 00 00",
          "count": 7
        },
        {
          "data": "6E 00 6E 00 00 00 00 00",
          "count": 4
        },
        {
          "data": "6E 00 6F 00 00 00 00 00",
          "count": 3
        },
        {
          "data": "6F 00 6A 00 00 00 00 00",
          "count": 3
        },
        {
          "data": "6F 00 6F 00 00 00 00 00",
          "count": 2
        },
        {
          "data": "70 00 6B 00 00 00 00 00",
          "count": 2
        }
      ]
    },
    {
      "ch": 1,
      "id_hex": "0x18F",
      "dlc": 8,
      "count": 1003,
      "unique": 1,
      "changing_bytes": [],
      "first": "FA 47 00 00 00 45 00 20",
      "last": "FA 47 00 00 00 45 00 20",
      "top": [
        {
          "data": "FA 47 00 00 00 45 00 20",
          "count": 1003
        }
      ]
    },
    {
      "ch": 0,
      "id_hex": "0x134",
      "dlc": 8,
      "count": 11,
      "unique": 1,
      "changing_bytes": [],
      "first": "03 00 00 01 00 00 10 00",
      "last": "03 00 00 01 00 00 10 00",
      "top": [
        {
          "data": "03 00 00 01 00 00 10 00",
          "count": 11
        }
      ]
    },
    {
      "ch": 1,
      "id_hex": "0x1BF",
      "dlc": 8,
      "count": 1003,
      "unique": 1,
      "changing_bytes": [],
      "first": "00 00 00 00 00 00 00 00",
      "last": "00 00 00 00 00 00 00 00",
      "top": [
        {
          "data": "00 00 00 00 00 00 00 00",
          "count": 1003
        }
      ]
    },
    {
      "ch": 1,
      "id_hex": "0x200",
      "dlc": 6,
      "count": 1003,
      "unique": 10,
      "changing_bytes": [
        0
      ],
      "first": "00 00 6F 00 00 00",
      "last": "00 00 6F 00 00 00",
      "top": [
        {
          "data": "00 00 6F 00 00 00",
          "count": 770
        },
        {
          "data": "67 00 6F 00 00 00",
          "count": 49
        },
        {
          "data": "63 00 6F 00 00 00",
          "count": 41
        },
        {
          "data": "61 00 6F 00 00 00",
          "count": 39
        },
        {
          "data": "62 00 6F 00 00 00",
          "count": 33
        },
        {
          "data": "64 00 6F 00 00 00",
          "count": 32
        },
        {
          "data": "65 00 6F 00 00 00",
          "count": 15
        },
        {
          "data": "66 00 6F 00 00 00",
          "count": 14
        },
        {
          "data": "68 00 6F 00 00 00",
          "count": 7
        },
        {
          "data": "69 00 6F 00 00 00",
          "count": 3
        }
      ]
    },
    {
      "ch": 1,
      "id_hex": "0x260",
      "dlc": 8,
      "count": 1003,
      "unique": 423,
      "changing_bytes": [
        0,
        1,
        2,
        5,
        6,
        7
      ],
      "first": "14 20 20 30 00 B6 71 29",
      "last": "15 21 21 30 00 B6 6E 0C",
      "top": [
        {
          "data": "14 20 20 30 00 B6 70 0C",
          "count": 14
        },
        {
          "data": "14 20 20 30 00 B6 70 39",
          "count": 14
        },
        {
          "data": "14 20 20 30 00 B6 6E 2D",
          "count": 13
        },
        {
          "data": "14 20 20 30 00 B6 6E 0F",
          "count": 12
        },
        {
          "data": "14 20 20 30 00 B6 6E 3C",
          "count": 12
        },
        {
          "data": "14 20 20 30 00 B6 71 1A",
          "count": 11
        },
        {
          "data": "14 20 20 30 00 B6 6D 3D",
          "count": 11
        },
        {
          "data": "14 20 20 30 00 B6 6E 1E",
          "count": 11
        },
        {
          "data": "14 20 20 30 00 B6 6D 2E",
          "count": 11
        },
        {
          "data": "14 20 20 30 00 B6 70 1B",
          "count": 10
        },
        {
          "data": "14 20 20 30 00 B6 70 2A",
          "count": 10
        },
        {
          "data": "14 20 20 30 00 B6 71 29",
          "count": 9
        }
      ]
    },
    {
      "ch": 1,
      "id_hex": "0x316",
      "dlc": 8,
      "count": 1003,
      "unique": 92,
      "changing_bytes": [
        1,
        2,
        3,
        4,
        5
      ],
      "first": "45 20 EC 0A 20 1E 00 76",
      "last": "45 21 D8 0A 21 1E 00 76",
      "top": [
        {
          "data": "45 20 F0 0A 20 1E 00 76",
          "count": 44
        },
        {
          "data": "45 21 CC 0A 21 1E 00 76",
          "count": 42
        },
        {
          "data": "45 20 E4 0A 20 1E 00 76",
          "count": 41
        },
        {
          "data": "45 1F EC 0A 1F 1D 00 76",
          "count": 38
        },
        {
          "data": "45 1F E4 0A 1F 1D 00 76",
          "count": 38
        },
        {
          "data": "45 1F F4 0A 1F 1D 00 76",
          "count": 29
        },
        {
          "data": "45 1F F8 0A 1F 1D 00 76",
          "count": 27
        },
        {
          "data": "45 1F 18 0B 1F 1D 00 76",
          "count": 25
        },
        {
          "data": "45 20 E0 0A 20 1E 00 76",
          "count": 24
        },
        {
          "data": "45 1E 18 0B 1E 1D 00 76",
          "count": 23
        },
        {
          "data": "45 20 D8 0A 20 1E 00 76",
          "count": 22
        },
        {
          "data": "45 1F E8 0A 1F 1D 00 76",
          "count": 22
        }
      ]
    },
    {
      "ch": 1,
      "id_hex": "0x329",
      "dlc": 8,
      "count": 1003,
      "unique": 8,
      "changing_bytes": [
        0,
        1
      ],
      "first": "0F AE 7F 10 11 20 00 18",
      "last": "40 AE 7F 10 11 20 00 18",
      "top": [
        {
          "data": "E2 AE 7F 10 11 20 00 18",
          "count": 228
        },
        {
          "data": "0F AE 7F 10 11 20 00 18",
          "count": 225
        },
        {
          "data": "40 AE 7F 10 11 20 00 18",
          "count": 216
        },
        {
          "data": "86 AE 7F 10 11 20 00 18",
          "count": 214
        },
        {
          "data": "40 AF 7F 10 11 20 00 18",
          "count": 36
        },
        {
          "data": "86 AF 7F 10 11 20 00 18",
          "count": 34
        },
        {
          "data": "0F AF 7F 10 11 20 00 18",
          "count": 30
        },
        {
          "data": "E2 AF 7F 10 11 20 00 18",
          "count": 20
        }
      ]
    },
    {
      "ch": 1,
      "id_hex": "0x2B0",
      "dlc": 5,
      "count": 1002,
      "unique": 16,
      "changing_bytes": [
        4
      ],
      "first": "57 00 00 07 05",
      "last": "57 00 00 07 BE",
      "top": [
        {
          "data": "57 00 00 07 05",
          "count": 63
        },
        {
          "data": "57 00 00 07 36",
          "count": 63
        },
        {
          "data": "57 00 00 07 27",
          "count": 63
        },
        {
          "data": "57 00 00 07 D8",
          "count": 63
        },
        {
          "data": "57 00 00 07 C9",
          "count": 63
        },
        {
          "data": "57 00 00 07 FA",
          "count": 63
        },
        {
          "data": "57 00 00 07 EB",
          "count": 63
        },
        {
          "data": "57 00 00 07 9C",
          "count": 63
        },
        {
          "data": "57 00 00 07 8D",
          "count": 63
        },
        {
          "data": "57 00 00 07 BE",
          "count": 63
        },
        {
          "data": "57 00 00 07 AF",
          "count": 62
        },
        {
          "data": "57 00 00 07 50",
          "count": 62
        }
      ]
    },
    {
      "ch": 1,
      "id_hex": "0x500",
      "dlc": 1,
      "count": 101,
      "unique": 1,
      "changing_bytes": [],
      "first": "3D",
      "last": "3D",
      "top": [
        {
          "data": "3D",
          "count": 101
        }
      ]
    },
    {
      "ch": 1,
      "id_hex": "0x153",
      "dlc": 8,
      "count": 1002,
      "unique": 15,
      "changing_bytes": [
        6,
        7
      ],
      "first": "20 00 10 FF 00 FF 00 2E",
      "last": "20 00 10 FF 00 FF B0 DE",
      "top": [
        {
          "data": "20 00 10 FF 00 FF 00 2E",
          "count": 67
        },
        {
          "data": "20 00 10 FF 00 FF 10 3E",
          "count": 67
        },
        {
          "data": "20 00 10 FF 00 FF 20 4E",
          "count": 67
        },
        {
          "data": "20 00 10 FF 00 FF 30 5E",
          "count": 67
        },
        {
          "data": "20 00 10 FF 00 FF 40 6E",
          "count": 67
        },
        {
          "data": "20 00 10 FF 00 FF 50 7E",
          "count": 67
        },
        {
          "data": "20 00 10 FF 00 FF 60 8E",
          "count": 67
        },
        {
          "data": "20 00 10 FF 00 FF 70 9E",
          "count": 67
        },
        {
          "data": "20 00 10 FF 00 FF 80 AE",
          "count": 67
        },
        {
          "data": "20 00 10 FF 00 FF 90 BE",
          "count": 67
        },
        {
          "data": "20 00 10 FF 00 FF A0 CE",
          "count": 67
        },
        {
          "data": "20 00 10 FF 00 FF B0 DE",
          "count": 67
        }
      ]
    },
    {
      "ch": 1,
      "id_hex": "0x381",
      "dlc": 8,
      "count": 501,
      "unique": 403,
      "changing_bytes": [
        1,
        2,
        5,
        6
      ],
      "first": "80 11 41 57 00 44 74 07",
      "last": "80 11 41 57 00 38 68 07",
      "top": [
        {
          "data": "80 01 41 57 00 4C 6C 07",
          "count": 2
        },
        {
          "data": "80 11 41 57 00 4D 7D 07",
          "count": 2
        },
        {
          "data": "80 01 41 57 00 4E 6E 07",
          "count": 2
        },
        {
          "data": "80 01 41 57 00 4F 6F 07",
          "count": 2
        },
        {
          "data": "80 11 41 57 00 50 80 07",
          "count": 2
        },
        {
          "data": "80 11 41 57 00 53 83 07",
          "count": 2
        },
        {
          "data": "80 01 41 57 00 54 74 07",
          "count": 2
        },
        {
          "data": "80 01 41 57 00 69 89 07",
          "count": 2
        },
        {
          "data": "80 01 41 57 00 6B 8B 07",
          "count": 2
        },
        {
          "data": "80 01 41 57 00 72 92 07",
          "count": 2
        },
        {
          "data": "80 01 41 57 00 76 96 07",
          "count": 2
        },
        {
          "data": "80 01 41 57 00 7B 9B 07",
          "count": 2
        }
      ]
    },
    {
      "ch": 1,
      "id_hex": "0x387",
      "dlc": 6,
      "count": 501,
      "unique": 1,
      "changing_bytes": [],
      "first": "03 00 00 00 00 03",
      "last": "03 00 00 00 00 03",
      "top": [
        {
          "data": "03 00 00 00 00 03",
          "count": 501
        }
      ]
    },
    {
      "ch": 1,
      "id_hex": "0x394",
      "dlc": 8,
      "count": 501,
      "unique": 62,
      "changing_bytes": [
        0,
        1,
        4,
        5,
        6
      ],
      "first": "FF 03 00 00 FF 83 15 81",
      "last": "FD 83 00 00 FD 83 11 81",
      "top": [
        {
          "data": "FF 43 00 00 FF 83 11 81",
          "count": 40
        },
        {
          "data": "FF E3 00 00 FF 83 17 81",
          "count": 37
        },
        {
          "data": "FF 63 00 00 FF 83 1F 81",
          "count": 35
        },
        {
          "data": "FF 83 00 00 FF 83 1D 81",
          "count": 33
        },
        {
          "data": "FF 23 00 00 FF 83 13 81",
          "count": 32
        },
        {
          "data": "FF C3 00 00 FF 83 19 81",
          "count": 32
        },
        {
          "data": "FF A3 00 00 FF 83 1B 81",
          "count": 31
        },
        {
          "data": "FF 03 00 00 FF 83 15 81",
          "count": 30
        },
        {
          "data": "00 A4 00 00 00 84 15 81",
          "count": 17
        },
        {
          "data": "00 C4 00 00 00 84 13 81",
          "count": 14
        },
        {
          "data": "00 E4 00 00 00 84 11 81",
          "count": 14
        },
        {
          "data": "00 04 00 00 00 84 1F 81",
          "count": 12
        }
      ]
    },
    {
      "ch": 1,
      "id_hex": "0x490",
      "dlc": 7,
      "count": 201,
      "unique": 1,
      "changing_bytes": [],
      "first": "00 00 08 20 00 00 00",
      "last": "00 00 08 20 00 00 00",
      "top": [
        {
          "data": "00 00 08 20 00 00 00",
          "count": 201
        }
      ]
    },
    {
      "ch": 0,
      "id_hex": "0x133",
      "dlc": 8,
      "count": 51,
      "unique": 1,
      "changing_bytes": [],
      "first": "00 00 00 00 00 00 00 82",
      "last": "00 00 00 00 00 00 00 82",
      "top": [
        {
          "data": "00 00 00 00 00 00 00 82",
          "count": 51
        }
      ]
    },
    {
      "ch": 1,
      "id_hex": "0x383",
      "dlc": 8,
      "count": 502,
      "unique": 16,
      "changing_bytes": [
        2,
        7
      ],
      "first": "13 2B B2 7C 9C 00 00 6A",
      "last": "13 2B 02 7C 9C 00 00 DA",
      "top": [
        {
          "data": "13 2B B2 7C 9C 00 00 6A",
          "count": 32
        },
        {
          "data": "13 2B C2 7C 9C 00 00 1A",
          "count": 32
        },
        {
          "data": "13 2B D2 7C 9C 00 00 0A",
          "count": 32
        },
        {
          "data": "13 2B E2 7C 9C 00 00 3A",
          "count": 32
        },
        {
          "data": "13 2B F2 7C 9C 00 00 2A",
          "count": 32
        },
        {
          "data": "13 2B 02 7C 9C 00 00 DA",
          "count": 32
        },
        {
          "data": "13 2B 12 7C 9C 00 00 CA",
          "count": 31
        },
        {
          "data": "13 2B 22 7C 9C 00 00 FA",
          "count": 31
        },
        {
          "data": "13 2B 32 7C 9C 00 00 EA",
          "count": 31
        },
        {
          "data": "13 2B 42 7C 9C 00 00 9A",
          "count": 31
        },
        {
          "data": "13 2B 52 7C 9C 00 00 8A",
          "count": 31
        },
        {
          "data": "13 2B 62 7C 9C 00 00 BA",
          "count": 31
        }
      ]
    },
    {
      "ch": 1,
      "id_hex": "0x390",
      "dlc": 7,
      "count": 501,
      "unique": 256,
      "changing_bytes": [
        4,
        5
      ],
      "first": "03 57 00 20 45 C2 03",
      "last": "03 57 00 20 39 B6 03",
      "top": [
        {
          "data": "03 57 00 20 45 C2 03",
          "count": 2
        },
        {
          "data": "03 57 00 20 46 C3 03",
          "count": 2
        },
        {
          "data": "03 57 00 20 47 C4 03",
          "count": 2
        },
        {
          "data": "03 57 00 20 48 C5 03",
          "count": 2
        },
        {
          "data": "03 57 00 20 49 C6 03",
          "count": 2
        },
        {
          "data": "03 57 00 20 4A C7 03",
          "count": 2
        },
        {
          "data": "03 57 00 20 4B C8 03",
          "count": 2
        },
        {
          "data": "03 57 00 20 4C C9 03",
          "count": 2
        },
        {
          "data": "03 57 00 20 4D CA 03",
          "count": 2
        },
        {
          "data": "03 57 00 20 4E CB 03",
          "count": 2
        },
        {
          "data": "03 57 00 20 4F CC 03",
          "count": 2
        },
        {
          "data": "03 57 00 20 50 CD 03",
          "count": 2
        }
      ]
    },
    {
      "ch": 1,
      "id_hex": "0x07F",
      "dlc": 8,
      "count": 11,
      "unique": 1,
      "changing_bytes": [],
      "first": "00 00 00 00 00 00 00 00",
      "last": "00 00 00 00 00 00 00 00",
      "top": [
        {
          "data": "00 00 00 00 00 00 00 00",
          "count": 11
        }
      ]
    },
    {
      "ch": 1,
      "id_hex": "0x410",
      "dlc": 8,
      "count": 51,
      "unique": 1,
      "changing_bytes": [],
      "first": "E4 1A 42 18 82 07 00 20",
      "last": "E4 1A 42 18 82 07 00 20",
      "top": [
        {
          "data": "E4 1A 42 18 82 07 00 20",
          "count": 51
        }
      ]
    },
    {
      "ch": 1,
      "id_hex": "0x58B",
      "dlc": 8,
      "count": 201,
      "unique": 1,
      "changing_bytes": [],
      "first": "11 00 04 00 00 00 00 20",
      "last": "11 00 04 00 00 00 00 20",
      "top": [
        {
          "data": "11 00 04 00 00 00 00 20",
          "count": 201
        }
      ]
    },
    {
      "ch": 1,
      "id_hex": "0x436",
      "dlc": 4,
      "count": 201,
      "unique": 1,
      "changing_bytes": [],
      "first": "00 00 00 00",
      "last": "00 00 00 00",
      "top": [
        {
          "data": "00 00 00 00",
          "count": 201
        }
      ]
    },
    {
      "ch": 1,
      "id_hex": "0x50E",
      "dlc": 8,
      "count": 51,
      "unique": 1,
      "changing_bytes": [],
      "first": "20 00 00 20 00 00 00 00",
      "last": "20 00 00 20 00 00 00 00",
      "top": [
        {
          "data": "20 00 00 20 00 00 00 00",
          "count": 51
        }
      ]
    },
    {
      "ch": 1,
      "id_hex": "0x520",
      "dlc": 8,
      "count": 101,
      "unique": 1,
      "changing_bytes": [],
      "first": "00 00 00 00 00 00 00 00",
      "last": "00 00 00 00 00 00 00 00",
      "top": [
        {
          "data": "00 00 00 00 00 00 00 00",
          "count": 101
        }
      ]
    },
    {
      "ch": 0,
      "id_hex": "0x132",
      "dlc": 8,
      "count": 11,
      "unique": 1,
      "changing_bytes": [],
      "first": "90 01 01 14 00 00 00 01",
      "last": "90 01 01 14 00 00 00 01",
      "top": [
        {
          "data": "90 01 01 14 00 00 00 01",
          "count": 11
        }
      ]
    },
    {
      "ch": 1,
      "id_hex": "0x541",
      "dlc": 8,
      "count": 101,
      "unique": 1,
      "changing_bytes": [],
      "first": "03 00 41 18 00 00 00 01",
      "last": "03 00 41 18 00 00 00 01",
      "top": [
        {
          "data": "03 00 41 18 00 00 00 01",
          "count": 101
        }
      ]
    },
    {
      "ch": 1,
      "id_hex": "0x553",
      "dlc": 8,
      "count": 51,
      "unique": 1,
      "changing_bytes": [],
      "first": "00 00 11 08 01 00 C0 00",
      "last": "00 00 11 08 01 00 C0 00",
      "top": [
        {
          "data": "00 00 11 08 01 00 C0 00",
          "count": 51
        }
      ]
    },
    {
      "ch": 1,
      "id_hex": "0x559",
      "dlc": 8,
      "count": 50,
      "unique": 1,
      "changing_bytes": [],
      "first": "00 40 00 00 20 00 00 40",
      "last": "00 40 00 00 20 00 00 40",
      "top": [
        {
          "data": "00 40 00 00 20 00 00 40",
          "count": 50
        }
      ]
    },
    {
      "ch": 1,
      "id_hex": "0x593",
      "dlc": 6,
      "count": 50,
      "unique": 1,
      "changing_bytes": [],
      "first": "00 10 FF FF FF FF",
      "last": "00 10 FF FF FF FF",
      "top": [
        {
          "data": "00 10 FF FF FF FF",
          "count": 50
        }
      ]
    },
    {
      "ch": 1,
      "id_hex": "0x4F4",
      "dlc": 8,
      "count": 201,
      "unique": 1,
      "changing_bytes": [],
      "first": "00 00 C0 00 00 00 00 01",
      "last": "00 00 C0 00 00 00 00 01",
      "top": [
        {
          "data": "00 00 C0 00 00 00 00 01",
          "count": 201
        }
      ]
    },
    {
      "ch": 1,
      "id_hex": "0x5C0",
      "dlc": 8,
      "count": 10,
      "unique": 1,
      "changing_bytes": [],
      "first": "00 00 00 00 00 00 00 00",
      "last": "00 00 00 00 00 00 00 00",
      "top": [
        {
          "data": "00 00 00 00 00 00 00 00",
          "count": 10
        }
      ]
    },
    {
      "ch": 0,
      "id_hex": "0x131",
      "dlc": 8,
      "count": 10,
      "unique": 1,
      "changing_bytes": [],
      "first": "15 00 FF 00 15 00 FF 00",
      "last": "15 00 FF 00 15 00 FF 00",
      "top": [
        {
          "data": "15 00 FF 00 15 00 FF 00",
          "count": 10
        }
      ]
    },
    {
      "ch": 0,
      "id_hex": "0x130",
      "dlc": 8,
      "count": 10,
      "unique": 1,
      "changing_bytes": [],
      "first": "00 FF FF 00 00 00 00 00",
      "last": "00 FF FF 00 00 00 00 00",
      "top": [
        {
          "data": "00 FF FF 00 00 00 00 00",
          "count": 10
        }
      ]
    },
    {
      "ch": 1,
      "id_hex": "0x492",
      "dlc": 8,
      "count": 200,
      "unique": 4,
      "changing_bytes": [
        7
      ],
      "first": "00 00 00 00 A6 80 7E B8",
      "last": "00 00 00 00 A6 80 7E F4",
      "top": [
        {
          "data": "00 00 00 00 A6 80 7E B8",
          "count": 50
        },
        {
          "data": "00 00 00 00 A6 80 7E 7C",
          "count": 50
        },
        {
          "data": "00 00 00 00 A6 80 7E 30",
          "count": 50
        },
        {
          "data": "00 00 00 00 A6 80 7E F4",
          "count": 50
        }
      ]
    },
    {
      "ch": 1,
      "id_hex": "0x50C",
      "dlc": 8,
      "count": 100,
      "unique": 30,
      "changing_bytes": [
        0,
        7
      ],
      "first": "88 4A 24 00 00 10 00 48",
      "last": "C8 4A 24 00 00 10 00 78",
      "top": [
        {
          "data": "C8 4A 24 00 00 10 00 28",
          "count": 6
        },
        {
          "data": "C8 4A 24 00 00 10 00 38",
          "count": 6
        },
        {
          "data": "C8 4A 24 00 00 10 00 48",
          "count": 6
        },
        {
          "data": "C8 4A 24 00 00 10 00 58",
          "count": 6
        },
        {
          "data": "C8 4A 24 00 00 10 00 68",
          "count": 6
        },
        {
          "data": "C8 4A 24 00 00 10 00 78",
          "count": 6
        },
        {
          "data": "C8 4A 24 00 00 10 00 88",
          "count": 5
        },
        {
          "data": "C8 4A 24 00 00 10 00 98",
          "count": 5
        },
        {
          "data": "C8 4A 24 00 00 10 00 A8",
          "count": 5
        },
        {
          "data": "C8 4A 24 00 00 10 00 B8",
          "count": 5
        },
        {
          "data": "C8 4A 24 00 00 10 00 C8",
          "count": 5
        },
        {
          "data": "C8 4A 24 00 00 10 00 D8",
          "count": 5
        }
      ]
    },
    {
      "ch": 0,
      "id_hex": "0x15D",
      "dlc": 8,
      "count": 50,
      "unique": 1,
      "changing_bytes": [],
      "first": "00 00 00 00 00 70 C0 F3",
      "last": "00 00 00 00 00 70 C0 F3",
      "top": [
        {
          "data": "00 00 00 00 00 70 C0 F3",
          "count": 50
        }
      ]
    },
    {
      "ch": 0,
      "id_hex": "0x1EB",
      "dlc": 8,
      "count": 50,
      "unique": 1,
      "changing_bytes": [],
      "first": "00 08 00 00 00 00 00 00",
      "last": "00 08 00 00 00 00 00 00",
      "top": [
        {
          "data": "00 08 00 00 00 00 00 00",
          "count": 50
        }
      ]
    },
    {
      "ch": 1,
      "id_hex": "0x507",
      "dlc": 4,
      "count": 100,
      "unique": 1,
      "changing_bytes": [],
      "first": "00 00 00 01",
      "last": "00 00 00 01",
      "top": [
        {
          "data": "00 00 00 01",
          "count": 100
        }
      ]
    },
    {
      "ch": 1,
      "id_hex": "0x502",
      "dlc": 4,
      "count": 100,
      "unique": 1,
      "changing_bytes": [],
      "first": "00 00 00 00",
      "last": "00 00 00 00",
      "top": [
        {
          "data": "00 00 00 00",
          "count": 100
        }
      ]
    },
    {
      "ch": 0,
      "id_hex": "0x135",
      "dlc": 8,
      "count": 50,
      "unique": 1,
      "changing_bytes": [],
      "first": "00 00 00 00 08 00 03 00",
      "last": "00 00 00 00 08 00 03 00",
      "top": [
        {
          "data": "00 00 00 00 08 00 03 00",
          "count": 50
        }
      ]
    },
    {
      "ch": 1,
      "id_hex": "0x53E",
      "dlc": 6,
      "count": 99,
      "unique": 1,
      "changing_bytes": [],
      "first": "00 08 00 00 80 0E",
      "last": "00 08 00 00 80 0E",
      "top": [
        {
          "data": "00 08 00 00 80 0E",
          "count": 99
        }
      ]
    },
    {
      "ch": 0,
      "id_hex": "0x44D",
      "dlc": 8,
      "count": 56,
      "unique": 1,
      "changing_bytes": [],
      "first": "4B 02 00 00 00 00 FF FF",
      "last": "4B 02 00 00 00 00 FF FF",
      "top": [
        {
          "data": "4B 02 00 00 00 00 FF FF",
          "count": 56
        }
      ]
    },
    {
      "ch": 1,
      "id_hex": "0x4A7",
      "dlc": 2,
      "count": 20,
      "unique": 1,
      "changing_bytes": [],
      "first": "01 00",
      "last": "01 00",
      "top": [
        {
          "data": "01 00",
          "count": 20
        }
      ]
    },
    {
      "ch": 1,
      "id_hex": "0x4E5",
      "dlc": 8,
      "count": 100,
      "unique": 6,
      "changing_bytes": [
        1,
        3
      ],
      "first": "80 5A 00 02 49 C4 00 00",
      "last": "80 5E 00 02 49 C4 00 00",
      "top": [
        {
          "data": "80 5A 00 02 49 C4 00 00",
          "count": 78
        },
        {
          "data": "80 5E 00 02 49 C4 00 00",
          "count": 16
        },
        {
          "data": "80 6E 00 03 49 C4 00 00",
          "count": 2
        },
        {
          "data": "80 72 00 03 49 C4 00 00",
          "count": 2
        },
        {
          "data": "80 5A 00 03 49 C4 00 00",
          "count": 1
        },
        {
          "data": "80 5E 00 03 49 C4 00 00",
          "count": 1
        }
      ]
    },
    {
      "ch": 1,
      "id_hex": "0x4E6",
      "dlc": 8,
      "count": 100,
      "unique": 5,
      "changing_bytes": [
        4,
        5,
        6
      ],
      "first": "49 C4 00 00 85 85 8B 00",
      "last": "49 C4 00 00 85 85 8A 00",
      "top": [
        {
          "data": "49 C4 00 00 85 85 8B 00",
          "count": 66
        },
        {
          "data": "49 C4 00 00 85 85 8A 00",
          "count": 31
        },
        {
          "data": "49 C4 00 00 85 84 8A 00",
          "count": 1
        },
        {
          "data": "49 C4 00 00 84 84 8B 00",
          "count": 1
        },
        {
          "data": "49 C4 00 00 85 85 89 00",
          "count": 1
        }
      ]
    },
    {
      "ch": 1,
      "id_hex": "0x4E7",
      "dlc": 8,
      "count": 100,
      "unique": 43,
      "changing_bytes": [
        0,
        1,
        3,
        5
      ],
      "first": "2D 80 00 07 00 82 00 00",
      "last": "2E 81 00 07 00 82 00 00",
      "top": [
        {
          "data": "2E 80 00 07 00 82 00 00",
          "count": 11
        },
        {
          "data": "2D 80 00 07 00 82 00 00",
          "count": 7
        },
        {
          "data": "2B 7C 00 08 00 82 00 00",
          "count": 5
        },
        {
          "data": "2F 81 00 07 00 82 00 00",
          "count": 5
        },
        {
          "data": "2C 7C 00 08 00 82 00 00",
          "count": 4
        },
        {
          "data": "2D 81 00 08 00 82 00 00",
          "count": 4
        },
        {
          "data": "2D 7A 00 07 00 82 00 00",
          "count": 3
        },
        {
          "data": "2C 7A 00 08 00 82 00 00",
          "count": 3
        },
        {
          "data": "2C 7B 00 08 00 82 00 00",
          "count": 3
        },
        {
          "data": "2D 7A 00 08 00 82 00 00",
          "count": 3
        },
        {
          "data": "2E 7B 00 08 00 82 00 00",
          "count": 3
        },
        {
          "data": "2A 7C 00 08 00 82 00 00",
          "count": 3
        }
      ]
    },
    {
      "ch": 1,
      "id_hex": "0x545",
      "dlc": 8,
      "count": 100,
      "unique": 48,
      "changing_bytes": [
        1,
        3,
        7
      ],
      "first": "D8 7D 00 8B 00 00 00 BA",
      "last": "D8 83 00 8B 00 00 00 BA",
      "top": [
        {
          "data": "D8 7F 00 8B 00 00 00 BA",
          "count": 6
        },
        {
          "data": "D8 6C 00 8B 00 00 00 BA",
          "count": 5
        },
        {
          "data": "D8 80 00 8B 00 00 00 BA",
          "count": 5
        },
        {
          "data": "D8 84 00 8B 00 00 00 BA",
          "count": 5
        },
        {
          "data": "D8 6E 00 8B 00 00 00 BA",
          "count": 4
        },
        {
          "data": "D8 71 00 8B 00 00 00 BA",
          "count": 4
        },
        {
          "data": "D8 70 00 8C 00 00 00 BA",
          "count": 4
        },
        {
          "data": "D8 74 00 8B 00 00 00 BA",
          "count": 4
        },
        {
          "data": "D8 70 00 8B 00 00 00 BA",
          "count": 4
        },
        {
          "data": "D8 81 00 8B 00 00 00 BA",
          "count": 4
        },
        {
          "data": "D8 7D 00 8B 00 00 00 BA",
          "count": 3
        },
        {
          "data": "D8 6E 00 8C 00 00 00 BA",
          "count": 3
        }
      ]
    },
    {
      "ch": 1,
      "id_hex": "0x547",
      "dlc": 8,
      "count": 100,
      "unique": 1,
      "changing_bytes": [],
      "first": "00 00 80 3D B9 47 CF 18",
      "last": "00 00 80 3D B9 47 CF 18",
      "top": [
        {
          "data": "00 00 80 3D B9 47 CF 18",
          "count": 100
        }
      ]
    },
    {
      "ch": 1,
      "id_hex": "0x549",
      "dlc": 8,
      "count": 100,
      "unique": 1,
      "changing_bytes": [],
      "first": "FF FF FF FF FF FF FF 7F",
      "last": "FF FF FF FF FF FF FF 7F",
      "top": [
        {
          "data": "FF FF FF FF FF FF FF 7F",
          "count": 100
        }
      ]
    },
    {
      "ch": 1,
      "id_hex": "0x556",
      "dlc": 8,
      "count": 100,
      "unique": 68,
      "changing_bytes": [
        0,
        1,
        2,
        3,
        5
      ],
      "first": "2D 7A E4 0A 00 1C 02 00",
      "last": "2E 7A D8 0A 00 1D 02 00",
      "top": [
        {
          "data": "2C 7A EC 0A 00 1C 02 00",
          "count": 5
        },
        {
          "data": "2D 7A D8 0A 00 1C 02 00",
          "count": 4
        },
        {
          "data": "2A 7A 24 0B 00 1C 02 00",
          "count": 4
        },
        {
          "data": "2D 7A E4 0A 00 1C 02 00",
          "count": 3
        },
        {
          "data": "2C 7A FC 0A 00 1C 02 00",
          "count": 3
        },
        {
          "data": "2E 7A C4 0A 00 1C 02 00",
          "count": 3
        },
        {
          "data": "2C 7A F8 0A 00 1C 02 00",
          "count": 3
        },
        {
          "data": "2E 7A D8 0A 00 1C 02 00",
          "count": 3
        },
        {
          "data": "2D 7A F0 0A 00 1C 02 00",
          "count": 2
        },
        {
          "data": "2D 7A E8 0A 00 1C 02 00",
          "count": 2
        },
        {
          "data": "2D 7A D0 0A 00 1C 02 00",
          "count": 2
        },
        {
          "data": "2C 7A E0 0A 00 1C 02 00",
          "count": 2
        }
      ]
    },
    {
      "ch": 1,
      "id_hex": "0x557",
      "dlc": 8,
      "count": 100,
      "unique": 55,
      "changing_bytes": [
        0,
        4,
        5
      ],
      "first": "7F 82 00 00 23 F1 01 00",
      "last": "80 82 00 00 24 F8 01 00",
      "top": [
        {
          "data": "7F 82 00 00 23 F1 01 00",
          "count": 7
        },
        {
          "data": "80 82 00 00 22 DC 01 00",
          "count": 6
        },
        {
          "data": "7F 82 00 00 23 F0 01 00",
          "count": 4
        },
        {
          "data": "80 82 00 00 22 E1 01 00",
          "count": 4
        },
        {
          "data": "7F 82 00 00 23 E0 01 00",
          "count": 3
        },
        {
          "data": "7F 82 00 00 23 DA 01 00",
          "count": 3
        },
        {
          "data": "7F 82 00 00 23 D9 01 00",
          "count": 3
        },
        {
          "data": "7F 82 00 00 24 F3 01 00",
          "count": 3
        },
        {
          "data": "7F 82 00 00 23 F2 01 00",
          "count": 3
        },
        {
          "data": "80 82 00 00 23 DB 01 00",
          "count": 3
        },
        {
          "data": "80 82 00 00 22 E3 01 00",
          "count": 3
        },
        {
          "data": "7E 82 00 00 23 E3 01 00",
          "count": 2
        }
      ]
    },
    {
      "ch": 1,
      "id_hex": "0x50A",
      "dlc": 8,
      "count": 50,
      "unique": 1,
      "changing_bytes": [],
      "first": "0B 00 00 00 00 00 00 00",
      "last": "0B 00 00 00 00 00 00 00",
      "top": [
        {
          "data": "0B 00 00 00 00 00 00 00",
          "count": 50
        }
      ]
    },
    {
      "ch": 1,
      "id_hex": "0x5CE",
      "dlc": 8,
      "count": 100,
      "unique": 65,
      "changing_bytes": [
        0,
        1,
        2,
        6
      ],
      "first": "25 25 5E 00 01 00 5B 00",
      "last": "26 26 5C 00 01 00 5E 00",
      "top": [
        {
          "data": "25 25 61 00 01 00 5C 00",
          "count": 6
        },
        {
          "data": "25 25 60 00 01 00 5C 00",
          "count": 5
        },
        {
          "data": "24 24 55 00 01 00 5B 00",
          "count": 4
        },
        {
          "data": "24 24 6E 00 01 00 59 00",
          "count": 4
        },
        {
          "data": "25 25 5F 00 01 00 5C 00",
          "count": 4
        },
        {
          "data": "25 25 62 00 01 00 5C 00",
          "count": 3
        },
        {
          "data": "24 23 6F 00 01 00 5A 00",
          "count": 3
        },
        {
          "data": "24 24 63 00 01 00 5B 00",
          "count": 3
        },
        {
          "data": "25 25 5E 00 01 00 5B 00",
          "count": 2
        },
        {
          "data": "24 24 5C 00 01 00 5C 00",
          "count": 2
        },
        {
          "data": "24 24 5A 00 01 00 5C 00",
          "count": 2
        },
        {
          "data": "24 24 57 00 01 00 5C 00",
          "count": 2
        }
      ]
    },
    {
      "ch": 1,
      "id_hex": "0x040",
      "dlc": 8,
      "count": 50,
      "unique": 1,
      "changing_bytes": [],
      "first": "00 00 11 04 02 00 00 00",
      "last": "00 00 11 04 02 00 00 00",
      "top": [
        {
          "data": "00 00 11 04 02 00 00 00",
          "count": 50
        }
      ]
    },
    {
      "ch": 1,
      "id_hex": "0x52A",
      "dlc": 8,
      "count": 50,
      "unique": 1,
      "changing_bytes": [],
      "first": "00 00 00 00 3E 00 00 00",
      "last": "00 00 00 00 3E 00 00 00",
      "top": [
        {
          "data": "00 00 00 00 3E 00 00 00",
          "count": 50
        }
      ]
    },
    {
      "ch": 0,
      "id_hex": "0x157",
      "dlc": 8,
      "count": 50,
      "unique": 1,
      "changing_bytes": [],
      "first": "02 00 00 00 00 00 00 00",
      "last": "02 00 00 00 00 00 00 00",
      "top": [
        {
          "data": "02 00 00 00 00 00 00 00",
          "count": 50
        }
      ]
    },
    {
      "ch": 1,
      "id_hex": "0x544",
      "dlc": 8,
      "count": 50,
      "unique": 1,
      "changing_bytes": [],
      "first": "FF 37 FF FF 00 00 00 00",
      "last": "FF 37 FF FF 00 00 00 00",
      "top": [
        {
          "data": "FF 37 FF FF 00 00 00 00",
          "count": 50
        }
      ]
    },
    {
      "ch": 0,
      "id_hex": "0x158",
      "dlc": 8,
      "count": 50,
      "unique": 1,
      "changing_bytes": [],
      "first": "FF C4 00 00 00 00 00 00",
      "last": "FF C4 00 00 00 00 00 00",
      "top": [
        {
          "data": "FF C4 00 00 00 00 00 00",
          "count": 50
        }
      ]
    },
    {
      "ch": 0,
      "id_hex": "0x169",
      "dlc": 8,
      "count": 50,
      "unique": 1,
      "changing_bytes": [],
      "first": "10 01 03 FF 14 00 20 00",
      "last": "10 01 03 FF 14 00 20 00",
      "top": [
        {
          "data": "10 01 03 FF 14 00 20 00",
          "count": 50
        }
      ]
    },
    {
      "ch": 0,
      "id_hex": "0x1DF",
      "dlc": 8,
      "count": 50,
      "unique": 1,
      "changing_bytes": [],
      "first": "3E FF 00 00 03 20 8F 00",
      "last": "3E FF 00 00 03 20 8F 00",
      "top": [
        {
          "data": "3E FF 00 00 03 20 8F 00",
          "count": 50
        }
      ]
    },
    {
      "ch": 0,
      "id_hex": "0x531",
      "dlc": 8,
      "count": 50,
      "unique": 1,
      "changing_bytes": [],
      "first": "7E 00 FF 00 00 00 00 00",
      "last": "7E 00 FF 00 00 00 00 00",
      "top": [
        {
          "data": "7E 00 FF 00 00 00 00 00",
          "count": 50
        }
      ]
    },
    {
      "ch": 0,
      "id_hex": "0x56E",
      "dlc": 8,
      "count": 50,
      "unique": 1,
      "changing_bytes": [],
      "first": "00 00 00 00 FF E0 00 00",
      "last": "00 00 00 00 FF E0 00 00",
      "top": [
        {
          "data": "00 00 00 00 FF E0 00 00",
          "count": 50
        }
      ]
    },
    {
      "ch": 0,
      "id_hex": "0x16A",
      "dlc": 8,
      "count": 50,
      "unique": 1,
      "changing_bytes": [],
      "first": "02 80 00 00 00 00 00 C3",
      "last": "02 80 00 00 00 00 00 C3",
      "top": [
        {
          "data": "02 80 00 00 00 00 00 C3",
          "count": 50
        }
      ]
    },
    {
      "ch": 0,
      "id_hex": "0x44B",
      "dlc": 8,
      "count": 55,
      "unique": 1,
      "changing_bytes": [],
      "first": "4D 02 00 00 00 00 FF FF",
      "last": "4D 02 00 00 00 00 FF FF",
      "top": [
        {
          "data": "4D 02 00 00 00 00 FF FF",
          "count": 55
        }
      ]
    },
    {
      "ch": 0,
      "id_hex": "0x17B",
      "dlc": 8,
      "count": 50,
      "unique": 1,
      "changing_bytes": [],
      "first": "00 00 00 00 00 00 00 00",
      "last": "00 00 00 00 00 00 00 00",
      "top": [
        {
          "data": "00 00 00 00 00 00 00 00",
          "count": 50
        }
      ]
    },
    {
      "ch": 0,
      "id_hex": "0x121",
      "dlc": 8,
      "count": 17,
      "unique": 1,
      "changing_bytes": [],
      "first": "1F FF 00 F0 7F FF FF FF",
      "last": "1F FF 00 F0 7F FF FF FF",
      "top": [
        {
          "data": "1F FF 00 F0 7F FF FF FF",
          "count": 17
        }
      ]
    },
    {
      "ch": 0,
      "id_hex": "0x136",
      "dlc": 8,
      "count": 17,
      "unique": 1,
      "changing_bytes": [],
      "first": "00 00 00 00 00 00 F0 00",
      "last": "00 00 00 00 00 00 F0 00",
      "top": [
        {
          "data": "00 00 00 00 00 00 F0 00",
          "count": 17
        }
      ]
    },
    {
      "ch": 1,
      "id_hex": "0x042",
      "dlc": 8,
      "count": 10,
      "unique": 1,
      "changing_bytes": [],
      "first": "15 FF 15 FF 00 00 00 00",
      "last": "15 FF 15 FF 00 00 00 00",
      "top": [
        {
          "data": "15 FF 15 FF 00 00 00 00",
          "count": 10
        }
      ]
    },
    {
      "ch": 1,
      "id_hex": "0x043",
      "dlc": 8,
      "count": 10,
      "unique": 1,
      "changing_bytes": [],
      "first": "00 10 40 02 03 00 00 10",
      "last": "00 10 40 02 03 00 00 10",
      "top": [
        {
          "data": "00 10 40 02 03 00 00 10",
          "count": 10
        }
      ]
    },
    {
      "ch": 1,
      "id_hex": "0x044",
      "dlc": 8,
      "count": 10,
      "unique": 1,
      "changing_bytes": [],
      "first": "82 FF FF 7E FF 03 00 08",
      "last": "82 FF FF 7E FF 03 00 08",
      "top": [
        {
          "data": "82 FF FF 7E FF 03 00 08",
          "count": 10
        }
      ]
    },
    {
      "ch": 1,
      "id_hex": "0x434",
      "dlc": 8,
      "count": 10,
      "unique": 1,
      "changing_bytes": [],
      "first": "01 00 00 00 00 00 00 00",
      "last": "01 00 00 00 00 00 00 00",
      "top": [
        {
          "data": "01 00 00 00 00 00 00 00",
          "count": 10
        }
      ]
    },
    {
      "ch": 1,
      "id_hex": "0x435",
      "dlc": 8,
      "count": 10,
      "unique": 1,
      "changing_bytes": [],
      "first": "7D 00 00 00 00 00 00 00",
      "last": "7D 00 00 00 00 00 00 00",
      "top": [
        {
          "data": "7D 00 00 00 00 00 00 00",
          "count": 10
        }
      ]
    },
    {
      "ch": 1,
      "id_hex": "0x5A0",
      "dlc": 8,
      "count": 10,
      "unique": 2,
      "changing_bytes": [
        5,
        6
      ],
      "first": "00 00 00 C0 25 05 A5 02",
      "last": "00 00 00 C0 25 27 95 02",
      "top": [
        {
          "data": "00 00 00 C0 25 05 A5 02",
          "count": 5
        },
        {
          "data": "00 00 00 C0 25 27 95 02",
          "count": 5
        }
      ]
    },
    {
      "ch": 1,
      "id_hex": "0x57F",
      "dlc": 8,
      "count": 5,
      "unique": 1,
      "changing_bytes": [],
      "first": "FF 00 00 FF 00 00 00 02",
      "last": "FF 00 00 FF 00 00 00 02",
      "top": [
        {
          "data": "FF 00 00 FF 00 00 00 02",
          "count": 5
        }
      ]
    },
    {
      "ch": 1,
      "id_hex": "0x5B0",
      "dlc": 4,
      "count": 10,
      "unique": 1,
      "changing_bytes": [],
      "first": "AC 81 12 00",
      "last": "AC 81 12 00",
      "top": [
        {
          "data": "AC 81 12 00",
          "count": 10
        }
      ]
    },
    {
      "ch": 1,
      "id_hex": "0x5BE",
      "dlc": 8,
      "count": 10,
      "unique": 1,
      "changing_bytes": [],
      "first": "04 00 00 FF 00 00 00 00",
      "last": "04 00 00 FF 00 00 00 00",
      "top": [
        {
          "data": "04 00 00 FF 00 00 00 00",
          "count": 10
        }
      ]
    },
    {
      "ch": 1,
      "id_hex": "0x5D3",
      "dlc": 8,
      "count": 10,
      "unique": 1,
      "changing_bytes": [],
      "first": "0F 00 00 00 00 00 00 00",
      "last": "0F 00 00 00 00 00 00 00",
      "top": [
        {
          "data": "0F 00 00 00 00 00 00 00",
          "count": 10
        }
      ]
    },
    {
      "ch": 1,
      "id_hex": "0x5D4",
      "dlc": 8,
      "count": 10,
      "unique": 1,
      "changing_bytes": [],
      "first": "00 00 00 00 00 00 00 00",
      "last": "00 00 00 00 00 00 00 00",
      "top": [
        {
          "data": "00 00 00 00 00 00 00 00",
          "count": 10
        }
      ]
    },
    {
      "ch": 0,
      "id_hex": "0x167",
      "dlc": 8,
      "count": 10,
      "unique": 1,
      "changing_bytes": [],
      "first": "00 00 00 00 07 C0 00 00",
      "last": "00 00 00 00 07 C0 00 00",
      "top": [
        {
          "data": "00 00 00 00 07 C0 00 00",
          "count": 10
        }
      ]
    },
    {
      "ch": 0,
      "id_hex": "0x5D7",
      "dlc": 8,
      "count": 10,
      "unique": 1,
      "changing_bytes": [],
      "first": "1C F0 00 00 00 12 81 AC",
      "last": "1C F0 00 00 00 12 81 AC",
      "top": [
        {
          "data": "1C F0 00 00 00 12 81 AC",
          "count": 10
        }
      ]
    }
  ]
}